{"localized_object_annotations": [{"mid": "/m/0jbk", "name": "Animal", "score": 0.81607836, "bounding_poly": {"normalized_vertices": [{"x": 0.42179534, "y": 0.3355646}, {"x": 0.6590876, "y": 0.3355646}, {"x": 0.6590876, "y": 0.42711112}, {"x": 0.42179534, "y": 0.42711112}]}}, {"mid": "/m/0jbk", "name": "Animal", "score": 0.8046288, "bounding_poly": {"normalized_vertices": [{"x": 0.12310847, "y": 0.46282795}, {"x": 0.47202802, "y": 0.46282795}, {"x": 0.47202802, "y": 0.66402644}, {"x": 0.12310847, "y": 0.66402644}]}}, {"mid": "/m/01g317", "name": "Person", "score": 0.7276482, "bounding_poly": {"normalized_vertices": [{"x": 0.027541848, "y": 0.017434005}, {"x": 0.109056525, "y": 0.017434005}, {"x": 0.109056525, "y": 0.20247827}, {"x": 0.027541848, "y": 0.20247827}]}}]}