{"localized_object_annotations": [{"mid": "/m/01g317", "name": "Person", "score": 0.8766516, "bounding_poly": {"normalized_vertices": [{"x": 0.549995, "y": 0.3294125}, {"x": 0.717377, "y": 0.3294125}, {"x": 0.717377, "y": 0.7150453}, {"x": 0.549995, "y": 0.7150453}]}}, {"mid": "/m/01g317", "name": "Person", "score": 0.85104984, "bounding_poly": {"normalized_vertices": [{"x": 0.29515454, "y": 0.3870131}, {"x": 0.5754151, "y": 0.3870131}, {"x": 0.5754151, "y": 0.7354515}, {"x": 0.29515454, "y": 0.7354515}]}}, {"mid": "/m/01g317", "name": "Person", "score": 0.7905745, "bounding_poly": {"normalized_vertices": [{"x": 0.80965537, "y": 0.35092655}, {"x": 0.9801805, "y": 0.35092655}, {"x": 0.9801805, "y": 0.7547963}, {"x": 0.80965537, "y": 0.7547963}]}}, {"mid": "/m/07mhn", "name": "Pants", "score": 0.7250169, "bounding_poly": {"normalized_vertices": [{"x": 0.59071684, "y": 0.52719975}, {"x": 0.7072444, "y": 0.52719975}, {"x": 0.7072444, "y": 0.65235066}, {"x": 0.59071684, "y": 0.65235066}]}}, {"mid": "/m/07mhn", "name": "Pants", "score": 0.7029111, "bounding_poly": {"normalized_vertices": [{"x": 0.2841331, "y": 0.44103655}, {"x": 0.5094497, "y": 0.44103655}, {"x": 0.5094497, "y": 0.72823304}, {"x": 0.2841331, "y": 0.72823304}]}}, {"mid": "/m/07mhn", "name": "Pants", "score": 0.6274581, "bounding_poly": {"normalized_vertices": [{"x": 0.830499, "y": 0.49704733}, {"x": 0.9388408, "y": 0.49704733}, {"x": 0.9388408, "y": 0.72559214}, {"x": 0.830499, "y": 0.72559214}]}}, {"mid": "/m/047vlmn", "name": "Outerwear", "score": 0.6024727, "bounding_poly": {"normalized_vertices": [{"x": 0.57281667, "y": 0.37954116}, {"x": 0.70791286, "y": 0.37954116}, {"x": 0.70791286, "y": 0.5497369}, {"x": 0.57281667, "y": 0.5497369}]}}, {"mid": "/m/09j2d", "name": "Clothing", "score": 0.53505135, "bounding_poly": {"normalized_vertices": [{"x": 0.29115415, "y": 0.40302077}, {"x": 0.5589202, "y": 0.40302077}, {"x": 0.5589202, "y": 0.731831}, {"x": 0.29115415, "y": 0.731831}]}}, {"mid": "/m/03gx245", "name": "Top", "score": 0.5252893, "bounding_poly": {"normalized_vertices": [{"x": 0.35563806, "y": 0.40700516}, {"x": 0.5435118, "y": 0.40700516}, {"x": 0.5435118, "y": 0.5446838}, {"x": 0.35563806, "y": 0.5446838}]}}]}